mkdocs_search_links_plugin/__init__.py
mkdocs_search_links_plugin/all_links_page.py
mkdocs_search_links_plugin/default.css
mkdocs_search_links_plugin/html_parser.py
mkdocs_search_links_plugin/listing-search.js
mkdocs_search_links_plugin/page_processor.py
mkdocs_search_links_plugin/search_page.py
mkdocs_search_links_plugin-0.1.0.dist-info/METADATA
mkdocs_search_links_plugin-0.1.0.dist-info/WHEEL
mkdocs_search_links_plugin-0.1.0.dist-info/entry_points.txt
mkdocs_search_links_plugin-0.1.0.dist-info/top_level.txt
mkdocs_search_links_plugin-0.1.0.dist-info/RECORD
