Metadata-Version: 2.4
Name: mkdocs-search-links-plugin
Version: 0.1.0
Summary: Create a page that contains all of your listings and/or a search function for listings
Home-page: https://github.com/six-two/mkdocs-search-links-plugin
Author: six-two
Author-email: pip@six-two.dev
License: MIT License
Classifier: Operating System :: POSIX :: Linux
Classifier: Programming Language :: Python :: 3
Classifier: Programming Language :: Python :: 3.9
Classifier: Programming Language :: Python :: 3.10
Classifier: Programming Language :: Python :: 3.11
Requires-Python: >=3.9
Requires-Dist: mkdocs>=1.5.0
Requires-Dist: beautifulsoup4
